bcp_exorcist-0.2.1.dist-info/METADATA
bcp_exorcist-0.2.1.dist-info/WHEEL
bcp_exorcist-0.2.1.dist-info/licenses/LICENSE
bcp_exorcist/__init__.py
bcp_exorcist/bcp_exorcist.pypy310-pp73-win_amd64.pyd
bcp_exorcist-0.2.1.dist-info/RECORD
